getitdone/__init__.py
getitdone/getitdone.py
getitdone-0.0.6.dist-info/entry_points.txt
getitdone-0.0.6.dist-info/LICENSE
getitdone-0.0.6.dist-info/WHEEL
getitdone-0.0.6.dist-info/METADATA
getitdone-0.0.6.dist-info/RECORD
