Metadata-Version: 2.1
Name: getitdone
Version: 0.0.6
Summary: Command line to-do list application
Home-page: https://github.com/ryanleonbutler/getitdone
License: AGPL-3.0
Author: Ryan Butler
Author-email: ryanleonbutler@gmail.com
Requires-Python: >=3.8,<4.0
Classifier: License :: OSI Approved :: GNU Affero General Public License v3
Classifier: Programming Language :: Python :: 3
Classifier: Programming Language :: Python :: 3.10
Classifier: Programming Language :: Python :: 3.8
Classifier: Programming Language :: Python :: 3.9
Requires-Dist: rich (>=12.0.1,<13.0.0)
Project-URL: Repository, https://github.com/ryanleonbutler/getitdone
